ocpm/__init__.py
ocpm/interaction.py
ocpm/main.py
ocpm/models.py
ocpm/data/OCKextRepos.yml
ocpm-1.0.3.dist-info/METADATA
ocpm-1.0.3.dist-info/WHEEL
ocpm-1.0.3.dist-info/entry_points.txt
ocpm-1.0.3.dist-info/top_level.txt
ocpm-1.0.3.dist-info/RECORD
