Metadata-Version: 2.1
Name: ocpm
Version: 1.0.3
Summary: OpenCore Package Manager by HyDEV
Home-page: https://github.com/hykilpikonna/ocpm
Author: Azalea Gui
Author-email: me@hydev.org
License: MIT
Classifier: License :: OSI Approved :: MIT License
Classifier: Programming Language :: Python :: 3
Classifier: Programming Language :: Python :: 3.7
Classifier: Programming Language :: Python :: 3.8
Classifier: Programming Language :: Python :: 3.9
Classifier: Programming Language :: Python :: 3.10
Requires-Dist: setuptools
Requires-Dist: hypy-utils
Requires-Dist: ruamel.yaml
Requires-Dist: requests
Requires-Dist: tqdm
Requires-Dist: packaging
